soundata/__init__.py
soundata/annotations.py
soundata/core.py
soundata/display_plot_utils.py
soundata/download_utils.py
soundata/io.py
soundata/jams_utils.py
soundata/validate.py
soundata/version.py
soundata/datasets/__init__.py
soundata/datasets/dcase23_task2.py
soundata/datasets/dcase23_task4b.py
soundata/datasets/dcase23_task6a.py
soundata/datasets/dcase23_task6b.py
soundata/datasets/dcase_bioacoustic.py
soundata/datasets/dcase_birdVox20k.py
soundata/datasets/eigenscape.py
soundata/datasets/eigenscape_raw.py
soundata/datasets/esc50.py
soundata/datasets/freefield1010.py
soundata/datasets/fsd50k.py
soundata/datasets/fsdnoisy18k.py
soundata/datasets/marco.py
soundata/datasets/singapura.py
soundata/datasets/starss2022.py
soundata/datasets/tau2019sse.py
soundata/datasets/tau2019uas.py
soundata/datasets/tau2020sse_nigens.py
soundata/datasets/tau2020uas_mobile.py
soundata/datasets/tau2021sse_nigens.py
soundata/datasets/tau2022uas_mobile.py
soundata/datasets/tut2017se.py
soundata/datasets/urbansed.py
soundata/datasets/urbansound8k.py
soundata/datasets/warblrb10k.py
soundata-1.0.1.dist-info/LICENSE
soundata-1.0.1.dist-info/METADATA
soundata-1.0.1.dist-info/WHEEL
soundata-1.0.1.dist-info/top_level.txt
soundata-1.0.1.dist-info/RECORD
