Metadata-Version: 2.1
Name: soundata
Version: 1.0.1
Summary: Python library for loading and working with sound datasets.
Author: Genís Plaja-Roglans, Guillem Cortès-Sebastià, Tanmay Khandelwal, Marius Miron, Xavier Serra, Juan Pablo Bello, Justin Salamon
Author-email: Magdalena Fuentes <mfuentes@nyu.edu>
Maintainer: Genís Plaja-Roglans, Guillem Cortès-Sebastià, Tanmay Khandelwal
Maintainer-email: Magdalena Fuentes <mfuentes@nyu.edu>
License: Copyright (c) 2016
Project-URL: Homepage, https://github.com/soundata/soundata
Project-URL: Documentation, https://soundata.readthedocs.io/en/latest/
Project-URL: Issues, https://github.com/soundata/soundata/issues
Project-URL: Releases, http://github.com/soundata/soundata/releases
Keywords: sound,dataset loader,audio
Classifier: License :: OSI Approved :: BSD License
Classifier: Programming Language :: Python
Classifier: Development Status :: 3 - Alpha
Classifier: Intended Audience :: Science/Research
Classifier: Topic :: Multimedia :: Sound/Audio :: Analysis
Classifier: Programming Language :: Python :: 3.7
Classifier: Programming Language :: Python :: 3.8
Classifier: Programming Language :: Python :: 3.9
Classifier: Programming Language :: Python :: 3.10
Requires-Python: >=3.7
License-File: LICENSE
Requires-Dist: librosa>=0.10.0
Requires-Dist: numpy>=1.21.6
Requires-Dist: pandas>=1.3.5
Requires-Dist: tqdm>=4.65.0
Requires-Dist: jams>=0.3.4
Requires-Dist: py7zr>=0.16.0
Provides-Extra: tests
Requires-Dist: requests>=2.31.0; extra == "tests"
Requires-Dist: pytest>=7.2.0; extra == "tests"
Requires-Dist: pytest-cov>=4.1.0; extra == "tests"
Requires-Dist: pytest-pep8>=1.0.6; extra == "tests"
Requires-Dist: pytest-mock>=3.10.0; extra == "tests"
Requires-Dist: pytest-localserver>=0.7.1; extra == "tests"
Requires-Dist: pytest-xdist>=2.3.0; extra == "tests"
Requires-Dist: future>=0.18.3; extra == "tests"
Requires-Dist: coveralls>=3.3.1; extra == "tests"
Requires-Dist: black>=23.3.0; extra == "tests"
Requires-Dist: flake8>=5.0.4; extra == "tests"
Requires-Dist: mypy>=0.982; extra == "tests"
Provides-Extra: docs
Requires-Dist: docutils==0.16; extra == "docs"
Requires-Dist: numpydoc; extra == "docs"
Requires-Dist: recommonmark; extra == "docs"
Requires-Dist: sphinx>=3.4.0; extra == "docs"
Requires-Dist: sphinxcontrib-napoleon; extra == "docs"
Requires-Dist: sphinx_rtd_theme; extra == "docs"
Requires-Dist: sphinx-togglebutton; extra == "docs"
Requires-Dist: ipywidgets>=8.1.1; extra == "docs"
Provides-Extra: plots
Requires-Dist: simpleaudio>=1.0.4; extra == "plots"
Requires-Dist: seaborn>=0.11.2; extra == "plots"
Requires-Dist: ipywidgets>=8.1.1; extra == "plots"
Requires-Dist: pydub>=0.25.1; extra == "plots"
